gitfluent/__init__.py
gitfluent/__main__.py
gitfluent/cli/__init__.py
gitfluent/cli/main.py
gitfluent/py.typed
gitfluent-0.1.0.dist-info/LICENSE
gitfluent-0.1.0.dist-info/METADATA
gitfluent-0.1.0.dist-info/WHEEL
gitfluent-0.1.0.dist-info/entry_points.txt
gitfluent-0.1.0.dist-info/RECORD
