Metadata-Version: 2.1
Name: gitfluent
Version: 0.1.0
Summary: 
Home-page: https://github.com/bit97/fluentgit
License: Apache-2.0
Author: Federico Bitondo
Requires-Python: >=3.8,<4.0
Classifier: License :: OSI Approved :: Apache Software License
Classifier: Programming Language :: Python :: 3
Classifier: Programming Language :: Python :: 3.8
Classifier: Programming Language :: Python :: 3.9
Classifier: Programming Language :: Python :: 3.10
Classifier: Programming Language :: Python :: 3.11
Requires-Dist: gitpython (>=3.1.38,<4.0.0)
Requires-Dist: rich (>=10.11.0)
Requires-Dist: typer (>=0.9.0)
Requires-Dist: typing-extensions (>=4.8.0,<5.0.0)
Project-URL: Repository, https://github.com/bit97/fluentgit
